ag_ui/__init__.py
ag_ui/core/__init__.py
ag_ui/core/events.py
ag_ui/core/types.py
ag_ui/encoder/__init__.py
ag_ui/encoder/encoder.py
ag_ui/py.typed
ag_ui_protocol-0.1.6.dist-info/LICENSE
ag_ui_protocol-0.1.6.dist-info/METADATA
ag_ui_protocol-0.1.6.dist-info/WHEEL
ag_ui_protocol-0.1.6.dist-info/RECORD
