Metadata-Version: 2.1
Name: ag-ui-protocol
Version: 0.1.6
Summary: 
Author: Markus Ecker
Author-email: markus.ecker@gmail.com
Requires-Python: >=3.9,<4.0
Classifier: Programming Language :: Python :: 3
Classifier: Programming Language :: Python :: 3.9
Classifier: Programming Language :: Python :: 3.10
Classifier: Programming Language :: Python :: 3.11
Classifier: Programming Language :: Python :: 3.12
Requires-Dist: pydantic (>=2.11.2,<3.0.0)
